dlms_encrypt_decrypt_tool/__init__.py
dlms_encrypt_decrypt_tool/dlms_cli.py
dlms_cli-1.1.dist-info/LICENSE
dlms_cli-1.1.dist-info/METADATA
dlms_cli-1.1.dist-info/WHEEL
dlms_cli-1.1.dist-info/entry_points.txt
dlms_cli-1.1.dist-info/top_level.txt
dlms_cli-1.1.dist-info/RECORD
