Metadata-Version: 2.1
Name: dlms-cli
Version: 1.1
Summary: DLMS CLI Tool for encrypt and decrypt APDU
Home-page: https://github.com/ric-geek/dlms-encrypt-decrypt-cli
Author: Riccardo
License: MIT
Platform: UNKNOWN
Classifier: License :: OSI Approved :: MIT License
Classifier: Programming Language :: Python :: 3 :: Only
Classifier: Programming Language :: Python :: 3
Classifier: Programming Language :: Python :: 3.6
Classifier: Programming Language :: Python :: 3.7
Classifier: Programming Language :: Python :: 3.8
Classifier: Programming Language :: Python :: 3.9
Classifier: Operating System :: Microsoft :: Windows
Classifier: Operating System :: POSIX :: Linux
Classifier: Development Status :: 5 - Production/Stable
Requires-Dist: cryptography
